pedro/__init__.py
pedro/api_client.py
pedro/cli.py
pedrocli-1.0.0.dist-info/METADATA
pedrocli-1.0.0.dist-info/WHEEL
pedrocli-1.0.0.dist-info/entry_points.txt
pedrocli-1.0.0.dist-info/top_level.txt
pedrocli-1.0.0.dist-info/RECORD
