Metadata-Version: 2.4
Name: pedroCLI
Version: 1.0.0
Summary: Pedro CLI — spectacular terminal AI client - Get PEDRO on your own pc
Author-email: emqnuele <help@gecowave.top>
Requires-Python: >=3.8
Requires-Dist: rich>=13.0.0
Requires-Dist: requests>=2.28.0
Requires-Dist: prompt-toolkit>=3.0.0
